LICENSE.rst
README.md
setup.cfg
setup.py
src/chargily_epay_gateway_django/__init__.py
src/chargily_epay_gateway_django/apps.py
src/chargily_epay_gateway_django/exceptions.py
src/chargily_epay_gateway_django/forms.py
src/chargily_epay_gateway_django/utils.py
src/chargily_epay_gateway_django/views.py
src/chargily_epay_gateway_django/migrations/__init__.py
src/chargily_epay_gateway_django_plugin.egg-info/PKG-INFO
src/chargily_epay_gateway_django_plugin.egg-info/SOURCES.txt
src/chargily_epay_gateway_django_plugin.egg-info/dependency_links.txt
src/chargily_epay_gateway_django_plugin.egg-info/requires.txt
src/chargily_epay_gateway_django_plugin.egg-info/top_level.txt