Metadata-Version: 2.1
Name: chargily-epay-gateway-django-plugin
Version: 0.1
Summary: UNKNOWN
Home-page: https://github.com/BeleganStartup/epay-gateway-django
Author: Chargily
Author-email: chargily@gmail.com
License: MIT
Project-URL: Global Website, https://chargily.com
Project-URL: DZ Website, https://chargily.com.dz
Project-URL: Github, https://github.com/Chargily/epay-gateway-django
Keywords: chargily,e-payment,integration,django
Platform: UNKNOWN
License-File: LICENSE.rst
